mlxtk/__init__.py
mlxtk/cwd.py
mlxtk/debug.py
mlxtk/doit_analyses/__init__.py
mlxtk/doit_analyses/collect.py
mlxtk/doit_analyses/expval.py
mlxtk/doit_analyses/fixed_ns.py
mlxtk/doit_analyses/gpop.py
mlxtk/doit_analyses/natpop.py
mlxtk/doit_analyses/output.py
mlxtk/doit_analyses/plot.py
mlxtk/doit_analyses/video.py
mlxtk/doit_compat.py
mlxtk/dvr.py
mlxtk/hashing.py
mlxtk/inout/__init__.py
mlxtk/inout/dmat.py
mlxtk/inout/dmat2.py
mlxtk/inout/eigenbasis.py
mlxtk/inout/expval.py
mlxtk/inout/fixed_ns.py
mlxtk/inout/g1.py
mlxtk/inout/g2.py
mlxtk/inout/gpop.py
mlxtk/inout/momentum_distribution.py
mlxtk/inout/natpop.py
mlxtk/inout/one_body_operator_matrix.py
mlxtk/inout/output.py
mlxtk/inout/psi.py
mlxtk/inout/spectrum.py
mlxtk/inout/tools.py
mlxtk/lock.py
mlxtk/log.py
mlxtk/operator/__init__.py
mlxtk/operator/mb_operator_specification.py
mlxtk/operator/operator_specification.py
mlxtk/parameter_scan.py
mlxtk/parameter_selection.py
mlxtk/parameters.py
mlxtk/plot/__init__.py
mlxtk/plot/cursor.py
mlxtk/plot/energy.py
mlxtk/plot/entropy.py
mlxtk/plot/expval.py
mlxtk/plot/gpop.py
mlxtk/plot/natpop.py
mlxtk/scripts/__init__.py
mlxtk/scripts/animate/dmat.py
mlxtk/scripts/animate/dmat2.py
mlxtk/scripts/animate/g1.py
mlxtk/scripts/animate/g2.py
mlxtk/scripts/animate/gpop.py
mlxtk/scripts/compute/dmat.py
mlxtk/scripts/compute/dmat2.py
mlxtk/scripts/compute/g1.py
mlxtk/scripts/compute/g2.py
mlxtk/scripts/create_slideshow.py
mlxtk/scripts/dmat2_gridrep.py
mlxtk/scripts/dmat2_gridrep_video.py
mlxtk/scripts/dmat_evec_slider.py
mlxtk/scripts/dmat_spf_slider.py
mlxtk/scripts/export/__init__.py
mlxtk/scripts/export/expval.py
mlxtk/scripts/export/gpop.py
mlxtk/scripts/export/output.py
mlxtk/scripts/fixed_ns.py
mlxtk/scripts/fixed_ns_table.py
mlxtk/scripts/gpop_model.py
mlxtk/scripts/grab_1b_eigenfunction.py
mlxtk/scripts/grab_spfs.py
mlxtk/scripts/mlxtkenv.py
mlxtk/scripts/plot/__init__.py
mlxtk/scripts/plot/energy.py
mlxtk/scripts/plot/energy_diff.py
mlxtk/scripts/plot/entropy.py
mlxtk-0.10.0.dist-info/entry_points.txt
mlxtk-0.10.0.dist-info/LICENSE.txt
mlxtk-0.10.0.dist-info/WHEEL
mlxtk-0.10.0.dist-info/METADATA
mlxtk-0.10.0.dist-info/RECORD
