Metadata-Version: 2.1
Name: mlxtk
Version: 0.10.0
Summary: Toolkit to design, run and analyze ML-MCTDH(X) simulations
Home-page: https://github.com/f-koehler/mlxtk
License: MIT
Keywords: physics,quantum,dynamics,ML-MCTDHX,MCTDHB,MCTDHF,dataflow
Author: Fabian Köhler
Author-email: fkoehler@physnet.uni-hamburg.de
Requires-Python: >=3.6.1,<3.9
Classifier: Development Status :: 3 - Alpha
Classifier: Environment :: Console
Classifier: Environment :: MacOS X
Classifier: Environment :: X11 Applications :: Qt
Classifier: Intended Audience :: Education
Classifier: Intended Audience :: Science/Research
Classifier: License :: OSI Approved :: MIT License
Classifier: Natural Language :: English
Classifier: Operating System :: MacOS
Classifier: Operating System :: POSIX :: Linux
Classifier: Operating System :: Unix
Classifier: Programming Language :: Python :: 3
Classifier: Programming Language :: Python :: 3 :: Only
Classifier: Programming Language :: Python :: 3.6
Classifier: Programming Language :: Python :: 3.7
Classifier: Programming Language :: Python :: 3.8
Classifier: Topic :: Education
Classifier: Topic :: Scientific/Engineering
Classifier: Topic :: Scientific/Engineering :: Physics
Requires-Dist: colorama (>=0.4.3,<0.5.0)
Requires-Dist: doit (>=0.33.1,<0.34.0)
Requires-Dist: future (>=0.18.2,<0.19.0)
Requires-Dist: h5py (>=2.10,<3.0)
Requires-Dist: jinja2 (>=2.11.2,<3.0.0)
Requires-Dist: matplotlib (>=3.3.2,<4.0.0)
Requires-Dist: numpy (>=1.19.2,<2.0.0)
Requires-Dist: numpy-stl (>=2.11.2,<3.0.0)
Requires-Dist: pandas (>=1.1.2,<2.0.0)
Requires-Dist: pathos (>=0.2.6,<0.3.0)
Requires-Dist: prompt-toolkit (>=3.0.7,<4.0.0)
Requires-Dist: pyside2 (>=5.15.1,<6.0.0)
Requires-Dist: pyyaml (>=5.3.1,<6.0.0)
Requires-Dist: scipy (>=1.5.2,<2.0.0)
Requires-Dist: sympy (>=1.6.2,<2.0.0)
Requires-Dist: tabulate (>=0.8.7,<0.9.0)
Requires-Dist: tqdm (>=4.50.0,<5.0.0)
Project-URL: Documentation, https://github.com/f-koehler/mlxtk
Project-URL: Repository, https://github.com/f-koehler/mlxtk
